tensorflow_rocm_enhanced/__init__.py
tensorflow_rocm_enhanced-0.0.1.dist-info/LICENSE
tensorflow_rocm_enhanced-0.0.1.dist-info/METADATA
tensorflow_rocm_enhanced-0.0.1.dist-info/WHEEL
tensorflow_rocm_enhanced-0.0.1.dist-info/top_level.txt
tensorflow_rocm_enhanced-0.0.1.dist-info/RECORD
